spat4apitesting/API_Call.py
spat4apitesting/Pipfile
spat4apitesting/Pipfile.lock
spat4apitesting/__init__.py
spat4apitesting/ad_hock.py
spat4apitesting/atr.py
spat4apitesting/conftest.py
spat4apitesting/setup.py
spat4apitesting/util.py
spat4apitesting/.pytest_cache/.gitignore
spat4apitesting/.pytest_cache/CACHEDIR.TAG
spat4apitesting/.pytest_cache/README.md
spat4apitesting/.pytest_cache/v/cache/lastfailed
spat4apitesting/.pytest_cache/v/cache/nodeids
spat4apitesting/.pytest_cache/v/cache/stepwise
spat4apitesting-0.0.209.dist-info/METADATA
spat4apitesting-0.0.209.dist-info/WHEEL
spat4apitesting-0.0.209.dist-info/licenses/LICENSE
spat4apitesting-0.0.209.dist-info/RECORD
