Metadata-Version: 2.1
Name: spat4apitesting
Version: 0.0.209
Summary: Simple Python API Testing
Project-URL: Homepage, https://github.com/Persnickety-Rose/spat
Project-URL: Bug Tracker, https://github.com/Persnickety-Rose/spat/issues
Author-email: Jasmine-Arabella Post <jasmine@Jasmine-Arabella.tech>
License-File: LICENSE
Classifier: License :: OSI Approved :: GNU General Public License v3 (GPLv3)
Classifier: Operating System :: OS Independent
Classifier: Programming Language :: Python :: 3
Requires-Python: >=3.7
